mapga/__init__.py
mapga/analyze.py
mapga/example.py
mapga/partition.py
mapga-0.0.3.dist-info/licenses/LICENCE
mapga-0.0.3.dist-info/METADATA
mapga-0.0.3.dist-info/WHEEL
mapga-0.0.3.dist-info/top_level.txt
mapga-0.0.3.dist-info/RECORD
