Metadata-Version: 2.4
Name: mapga
Version: 0.0.3
Summary: Model Analysis and Partitioning with Genetic Algorithms
Author-email: Sandro Sage <sandro.sage@iis.fraunhofer.de>
License-Expression: MIT
Project-URL: Homepage, https://github.com/pypa/sampleproject
Project-URL: Issues, https://github.com/pypa/sampleproject/issues
Classifier: Programming Language :: Python :: 3
Classifier: Operating System :: OS Independent
Requires-Python: >=3.9
License-File: LICENCE
Requires-Dist: keras==2.14.0
Requires-Dist: tensorflow==2.14.0
Requires-Dist: numpy==1.26.4
Requires-Dist: matplotlib<4.0.0,>=3.10.1
Requires-Dist: deap<2.0.0,>=1.4.2
Dynamic: license-file
